setup.py
gitbox/Pubnub.py
gitbox/__init__.py
gitbox/cli.py
gitbox/deamon.py
gitbox/notify.py
gitbox/watchman.py
gitbox.egg-info/PKG-INFO
gitbox.egg-info/SOURCES.txt
gitbox.egg-info/dependency_links.txt
gitbox.egg-info/entry_points.txt
gitbox.egg-info/requires.txt
gitbox.egg-info/top_level.txt