Metadata-Version: 1.0
Name: gitbox
Version: 0.1.3
Summary: Simple and automatically sync deamon for git repositories. A dropbox alternative.
Home-page: https://github.com/monocult/gitbox
Author: Christoph Jerolimov & Daniel Nuemm
Author-email: christoph@jerolimov.de, daniel.nuemm@googlemail.com
License: UNKNOWN
Platform: UNKNOWN
